Workbook

Sheet PESQUISA
A1: CNAE | B1: DESCRIÇÃO | C1: VALOR | E1: CNAE a TRIBUTAR
B2: =IF(A2="","",VLOOKUP(A2,'ANEXO CTMI'!A$1:P$2043,8)) | C2: =IF(A2="","",VLOOKUP(A2,'ANEXO CTMI'!A$1:P$2043,10)) | D2: =IF(A2="","",MAX(C$2:C$41)) | E2: =IF(A2="","",IF(C2=D2,"X",""))
B3: =IF(A3="","",VLOOKUP(A3,'ANEXO CTMI'!A$1:P$2043,8)) | C3: =IF(A3="","",VLOOKUP(A3,'ANEXO CTMI'!A$1:P$2043,10)) | D3: =IF(A3="","",MAX(C$2:C$41)) | E3: =IF(A3="","",IF(C3=D3,"X",""))
B4: =IF(A4="","",VLOOKUP(A4,'ANEXO CTMI'!A$1:P$2043,8)) | C4: =IF(A4="","",VLOOKUP(A4,'ANEXO CTMI'!A$1:P$2043,10)) | D4: =IF(A4="","",MAX(C$2:C$41)) | E4: =IF(A4="","",IF(C4=D4,"X",""))
B5: =IF(A5="","",VLOOKUP(A5,'ANEXO CTMI'!A$1:P$2043,8)) | C5: =IF(A5="","",VLOOKUP(A5,'ANEXO CTMI'!A$1:P$2043,10)) | D5: =IF(A5="","",MAX(C$2:C$41)) | E5: =IF(A5="","",IF(C5=D5,"X",""))
B6: =IF(A6="","",VLOOKUP(A6,'ANEXO CTMI'!A$1:P$2043,8)) | C6: =IF(A6="","",VLOOKUP(A6,'ANEXO CTMI'!A$1:P$2043,10)) | D6: =IF(A6="","",MAX(C$2:C$41)) | E6: =IF(A6="","",IF(C6=D6,"X",""))
B7: =IF(A7="","",VLOOKUP(A7,'ANEXO CTMI'!A$1:P$2043,8)) | C7: =IF(A7="","",VLOOKUP(A7,'ANEXO CTMI'!A$1:P$2043,10)) | D7: =IF(A7="","",MAX(C$2:C$41)) | E7: =IF(A7="","",IF(C7=D7,"X",""))
B8: =IF(A8="","",VLOOKUP(A8,'ANEXO CTMI'!A$1:P$2043,8)) | C8: =IF(A8="","",VLOOKUP(A8,'ANEXO CTMI'!A$1:P$2043,10)) | D8: =IF(A8="","",MAX(C$2:C$41)) | E8: =IF(A8="","",IF(C8=D8,"X",""))
B9: =IF(A9="","",VLOOKUP(A9,'ANEXO CTMI'!A$1:P$2043,8)) | C9: =IF(A9="","",VLOOKUP(A9,'ANEXO CTMI'!A$1:P$2043,10)) | D9: =IF(A9="","",MAX(C$2:C$41)) | E9: =IF(A9="","",IF(C9=D9,"X",""))
B10: =IF(A10="","",VLOOKUP(A10,'ANEXO CTMI'!A$1:P$2043,8)) | C10: =IF(A10="","",VLOOKUP(A10,'ANEXO CTMI'!A$1:P$2043,10)) | D10: =IF(A10="","",MAX(C$2:C$41)) | E10: =IF(A10="","",IF(C10=D10,"X",""))
B11: =IF(A11="","",VLOOKUP(A11,'ANEXO CTMI'!A$1:P$2043,8)) | C11: =IF(A11="","",VLOOKUP(A11,'ANEXO CTMI'!A$1:P$2043,10)) | D11: =IF(A11="","",MAX(C$2:C$41)) | E11: =IF(A11="","",IF(C11=D11,"X",""))
B12: =IF(A12="","",VLOOKUP(A12,'ANEXO CTMI'!A$1:P$2043,8)) | C12: =IF(A12="","",VLOOKUP(A12,'ANEXO CTMI'!A$1:P$2043,10)) | D12: =IF(A12="","",MAX(C$2:C$41)) | E12: =IF(A12="","",IF(C12=D12,"X",""))
B13: =IF(A13="","",VLOOKUP(A13,'ANEXO CTMI'!A$1:P$2043,8)) | C13: =IF(A13="","",VLOOKUP(A13,'ANEXO CTMI'!A$1:P$2043,10)) | D13: =IF(A13="","",MAX(C$2:C$41)) | E13: =IF(A13="","",IF(C13=D13,"X",""))
... B41: =IF(A41="","",VLOOKUP(A41,'ANEXO CTMI'!A$1:P$2043,8)) | C41: =IF(A41="","",VLOOKUP(A41,'ANEXO CTMI'!A$1:P$2043,10)) | D41: =IF(A41="","",MAX(C$2:C$41)) | E41: =IF(A41="","",IF(C41=D41,"X",""))

Sheet ANEXO CTMI
A1: 0 | C1: ANEXO | D1: setor | E1: tipo | F1: esp | H1: RETORNO PARA CODCONT | I1: unid | J1: UFITA/ANO ALVARÁ | L1: Mesnsal | M1: tempo | N1: OBS
A2: 999 | H2: DESCRIÇÃO DA ATIVIDADE | K2: Base de Cálculo | L2: % ISS EMP /AUT | M2: ISS em UFITAS (MENSAL)
A3: 111301 | G3: T.F.I.F. | H3: Cultivo de arroz | J3: 31.68
A4: 111302 | G4: T.F.I.F. | H4: Cultivo de milho | J4: 31.68
A5: 111303 | G5: T.F.I.F. | H5: Cultivo de trigo | J5: 31.68
A6: 111399 | G6: T.F.I.F. | H6: Cultivo de outros cereais não especificados anteriormente | J6: 31.68
A7: 112101 | G7: T.F.I.F. | H7: Cultivo de algodão herbáceo | J7: 31.68
A8: 112102 | G8: T.F.I.F. | H8: Cultivo de juta | J8: 31.68
A9: 112199 | G9: T.F.I.F. | H9: Cultivo de outras fibras de lavoura temporária não especificadas anteriormente | J9: 31.68
A10: 113000 | G10: T.F.I.F. | H10: Cultivo de cana-de-açúcar | J10: 31.68
A11: 114800 | G11: T.F.I.F. | H11: Cultivo de fumo | J11: 31.68
A12: 115600 | G12: T.F.I.F. | H12: Cultivo de soja | J12: 31.68
A13: 116401 | G13: T.F.I.F. | H13: Cultivo de amendoim | J13: 31.68
A14: 116402 | G14: T.F.I.F. | H14: Cultivo de girassol | J14: 31.68
... A74: 159899 | G74: T.F.I.F. | H74: Criação de outros animais não especificados anteriormente | J74: 31.68
A75: 161001 | G75: T.F.I.F. | H75: Serviço de pulverização e controle de pragas agrícolas | J75: 12.67 | L75: 2
A76: 161002 | G76: T.F.I.F. | H76: Serviço de poda de árvores para lavouras | J76: 12.67 | L76: 3
A77: 161003 | G77: T.F.I.F. | H77: Serviço de preparação de terreno, cultivo e colheita | J77: 0
A78: 161099 | G78: T.F.I.F. | H78: Atividades de apoio à agricultura não especificadas anteriormente | J78: 31.68 | L78: 5
A79: 162801 | G79: T.F.I.F. | H79: Serviço de inseminação artificial em animais | J79: 31.68 | L79: 5
A80: 162802 | G80: T.F.I.F. | H80: Serviço de tosquiamento de ovinos | J80: 31.68 | L80: 5
A81: 162803 | G81: T.F.I.F. | H81: Serviço de manejo de animais | J81: 31.68 | L81: 5
A82: 162899 | G82: T.F.I.F. | H82: Atividades de apoio à pecuária não especificadas anteriormente | J82: 31.68 | L82: 5
A83: 163600 | G83: T.F.I.F. | H83: Atividades de pós-colheita | J83: 0
A84: 170900 | G84: T.F.I.F. | H84: Caça e serviços relacionados | J84: 31.68 | L84: 5
A85: 210101 | G85: T.F.I.F. | H85: Cultivo de eucalipto | J85: 31.68
A86: 210102 | G86: T.F.I.F. | H86: Cultivo de acácia-negra | J86: 31.68
A87: 210103 | G87: T.F.I.F. | H87: Cultivo de pinus | J87: 31.68
A88: 210104 | G88: T.F.I.F. | H88: Cultivo de teca | J88: 31.68
A89: 210105 | G89: T.F.I.F. | H89: Cultivo de espécies madeireiras, exceto eucalipto, acácia-negra, pinus e teca | J89: 31.68
A90: 210106 | G90: T.F.I.F. | H90: Cultivo de mudas em viveiros florestais | J90: 31.68 | L90: 2
A91: 210107 | G91: T.F.I.F. | H91: Extração de madeira em florestas plantadas | J91: 31.68 | L91: 5
A92: 210108 | G92: T.F.I.F. | H92: Produção de carvão vegetal - florestas plantadas | J92: 31.68 | L92: 5
A93: 210109 | G93: T.F.I.F. | H93: Produção de casca de acácia-negra - florestas plantadas | J93: 31.68 | L93: 5
A94: 210199 | G94: T.F.I.F. | H94: Produção de produtos não-madeireiros não especificados anteriormente em florestas plantadas | J94: 31.68 | L94: 5
A95: 220901 | G95: T.F.I.F. | H95: Extração de madeira em florestas nativas | J95: 31.68 | L95: 5
A96: 220902 | G96: T.F.I.F. | H96: Produção de carvão vegetal - florestas nativas | J96: 31.68 | L96: 5
A97: 220903 | G97: T.F.I.F. | H97: Coleta de castanha-do-pará em florestas nativas | J97: 31.68 | L97: 5
A98: 220904 | G98: T.F.I.F. | H98: Coleta de látex em florestas nativas | J98: 31.68 | L98: 5
A99: 220905 | G99: T.F.I.F. | H99: Coleta de palmito em florestas nativas | J99: 31.68 | L99: 5
A100: 220906 | G100: T.F.I.F. | H100: Conservação de florestas nativas | J100: 31.68 | L100: 2
A101: 220999 | G101: T.F.I.F. | H101: Coleta de produtos não-madeireiros não especificados anteriormente em florestas nativas | J101: 31.68 | L101: 5
A102: 230600 | G102: T.F.I.F. | H102: Atividades de apoio à produção florestal | J102: 31.68 | L102: 2
A103: 311601 | G103: T.F.I.F. | H103: Pesca de peixes em água salgada | J103: 0
A104: 311602 | G104: T.F.I.F. | H104: Pesca de crustáceos e moluscos em água salgada | J104: 0
A105: 311603 | G105: T.F.I.F. | H105: Coleta de outros produtos marinhos | J105: 0
A106: 311604 | G106: T.F.I.F. | H106: Atividades de apoio à pesca em água salgada | J106: 31.68 | L106: 5
A107: 312401 | G107: T.F.I.F. | H107: Pesca de peixes em água doce | J107: 0
A108: 312402 | G108: T.F.I.F. | H108: Pesca de crustáceos e moluscos em água doce | J108: 0
A109: 312403 | G109: T.F.I.F. | H109: Coleta de outros produtos aquáticos de água doce | J109: 0
A110: 312404 | G110: T.F.I.F. | H110: Atividades de apoio à pesca em água doce | J110: 31.68 | L110: 5
A111: 321301 | G111: T.F.I.F. | H111: Criação de peixes em água salgada e salobra | J111: 31.68 | L111: 5
A112: 321302 | G112: T.F.I.F. | H112: Criação de camarões em água salgada e salobra | J112: 31.68 | L112: 5
A113: 321303 | G113: T.F.I.F. | H113: Criação de ostras e mexilhões em água salgada e salobra | J113: 31.68 | L113: 5
A114: 321304 | G114: T.F.I.F. | H114: Criação de peixes ornamentais em água salgada e salobra | J114: 31.68 | L114: 5
A115: 321305 | G115: T.F.I.F. | H115: Atividades de apoio à aqüicultura em água salgada e salobra | J115: 31.68 | L115: 5
A116: 321399 | G116: T.F.I.F. | H116: Cultivos e semicultivos da aqüicultura em água salgada e salobra não especificados anteriormente | J116: 31.68 | L116: 5
A117: 322101 | G117: T.F.I.F. | H117: Criação de peixes em água doce | J117: 31.68 | L117: 5
A118: 322102 | G118: T.F.I.F. | H118: Criação de camarões em água doce | J118: 31.68 | L118: 5
A119: 322103 | G119: T.F.I.F. | H119: Criação de ostras e mexilhões em água doce | J119: 31.68 | L119: 5
A120: 322104 | G120: T.F.I.F. | H120: Criação de peixes ornamentais em água doce | J120: 31.68 | L120: 5
A121: 322105 | G121: T.F.I.F. | H121: Ranicultura | J121: 31.68 | L121: 5
... A124: 322199 | G124: T.F.I.F. | H124: Cultivos e semicultivos da aqüicultura em água doce não especificados anteriormente | J124: 31.68 | L124: 5
A125: 500301 | G125: T.F.I.F. | H125: Extração de carvão mineral | J125: 31.68
A126: 500302 | G126: T.F.I.F. | H126: Beneficiamento de carvão mineral | J126: 63.35
A127: 600001 | G127: T.F.I.F. | H127: Extração de petróleo e gás natural ➭ (NR LC 284/2022) | J127: 316.76 | L127: 2
A128: 600002 | G128: T.F.I.F. | H128: Extração e beneficiamento de xisto | J128: 63.35
A129: 600003 | G129: T.F.I.F. | H129: Extração e beneficiamento de areias betuminosas | J129: 63.35
A130: 710301 | G130: T.F.I.F. | H130: Extração de minério de ferro | J130: 31.68
A131: 710302 | G131: T.F.I.F. | H131: Pelotização, sinterização e outros beneficiamentos de minério de ferro | J131: 63.35
A132: 721901 | G132: T.F.I.F. | H132: Extração de minério de alumínio | J132: 31.68
A133: 721902 | G133: T.F.I.F. | H133: Beneficiamento de minério de alumínio | J133: 63.35
A134: 722701 | G134: T.F.I.F. | H134: Extração de minério de estanho | J134: 31.68
A135: 722702 | G135: T.F.I.F. | H135: Beneficiamento de minério de estanho | J135: 63.35
A136: 723501 | G136: T.F.I.F. | H136: Extração de minério de manganês | J136: 31.68
A137: 723502 | G137: T.F.I.F. | H137: Beneficiamento de minério de manganês | J137: 63.35
A138: 724301 | G138: T.F.I.F. | H138: Extração de minério de metais preciosos | J138: 31.68
A139: 724302 | G139: T.F.I.F. | H139: Beneficiamento de minério de metais preciosos | J139: 63.35
... A155: 810010 | G155: T.F.I.F. | H155: Beneficiamento de gesso e caulim associado à extração | J155: 63.35
A156: 810099 | G156: T.F.I.F. | H156: Extração e britamento de pedras e outros materiais para construção e beneficiamento associado | J156: 126.7 | L156: 5
A157: 891600 | G157: T.F.I.F. | H157: Extração de minerais para fabricação de adubos, fertilizantes e outros produtos químicos | J157: 31.68
A158: 892401 | G158: T.F.I.F. | H158: Extração de sal marinho | J158: 0
A159: 892402 | G159: T.F.I.F. | H159: Extração de sal-gema | J159: 0
A160: 892403 | G160: T.F.I.F. | H160: Refino e outros tratamentos do sal | J160: 0
A161: 893200 | G161: T.F.I.F. | H161: Extração de gemas (pedras preciosas e semipreciosas) | J161: 126.7
A162: 899101 | G162: T.F.I.F. | H162: Extração de grafita | J162: 126.7
A163: 899102 | G163: T.F.I.F. | H163: Extração de quartzo | J163: 126.7
A164: 899103 | G164: T.F.I.F. | H164: Extração de amianto | J164: 126.7
A165: 899199 | G165: T.F.I.F. | H165: Extração de outros minerais não-metálicos não especificados anteriormente | J165: 31.68
A166: 910600 | G166: T.F.I.F. | H166: Atividades de apoio à extração de petróleo e gás natural ➭ (NR LC 284/2022) | J166: 126.7 | L166: 2
A167: 990401 | G167: T.F.I.F. | H167: Atividades de apoio à extração de minério de ferro | J167: 31.68 | L167: 5
A168: 990402 | G168: T.F.I.F. | H168: Atividades de apoio à extração de minerais metálicos não-ferrosos | J168: 31.68 | L168: 5
A169: 990403 | G169: T.F.I.F. | H169: Atividades de apoio à extração de minerais não-metálicos | J169: 31.68 | L169: 5
A170: 1011201 | G170: T.F.I.F. | H170: Frigorífico - abate de bovinos | J170: 50.68
A171: 1011202 | G171: T.F.I.F. | H171: Frigorífico - abate de eqüinos | J171: 50.68
A172: 1011203 | G172: T.F.I.F. | H172: Frigorífico - abate de ovinos e caprinos | J172: 50.68
A173: 1011204 | G173: T.F.I.F. | H173: Frigorífico - abate de bufalinos | J173: 50.68
A174: 1011205 | G174: T.F.I.F. | H174: Matadouro - abate de reses sob contrato, exceto abate de suínos | J174: 50.68 | L174: 5
A175: 1012101 | G175: T.F.I.F. | H175: Abate de aves | J175: 31.68
A176: 1012102 | G176: T.F.I.F. | H176: Abate de pequenos animais | J176: 31.68
...

Sheet ISS 2024
A1: ATIVIDADES | B1: Base de cálculo Estimada - Mensal - UFITAS | C1: ALÍQUOTAS % | D1: ISS EM UFITAS
A2: 1 - Profissionais Autônomos Nível Superior:
A3: a) Médicos, dentistas e veterinários | B3: 1092.41 | C3: 0.035 | D3: 38.23
A4: b) Advogados | B4: 1092.41 | C4: 0.035 | D4: 38.23
A5: c) Engenheiro, Arquitetos | B5: 728.27 | C5: 0.035 | D5: 25.48
A6: d) Administradores, economistas e contadores | B6: 728.27 | C6: 0.035 | D6: 25.48
A7: e) Fisioterapeutas, psicólogos e Terapeutas | B7: 728.27 | C7: 0.035 | D7: 25.48
A8: f) Demais profissionais de nível superior | B8: 582.62 | C8: 0.035 | D8: 20.39
A9: 2 - Profissionais Autônomos Nível Médio:
A10: a) Despachante, representantes e corretores | B10: 509.79 | C10: 0.035 | D10: 17.84
A11: b) Mecânicos | B11: 364.13 | C11: 0.035 | D11: 12.74
A12: c) Demais profissionais de nível médio | B12: 254.89 | C12: 0.035 | D12: 8.92
A13: 3 - Profissionais Autônomos Nível Elementar:
A14: a) Motorista (Qualquer modalidade de transporte, inclusive os motoristas auxiliares) (NR LC 238/2018) | B14: 338.82 | C14: 0.035 | D14: 11.86
A15: b) Monitor de Transporte Escolar (NR LC 238/2018) | B15: 148.66 | C15: 0.035 | D15: 5.2
A16: c) Carpinteiros, bombeiro-hidráulico, pedreiros e marceneiros | B16: 364.13 | C16: 0.035 | D16: 12.74
A17: d) Demais Profissionais de Nível Elementar | B17: 218.48 | C17: 0.035 | D17: 7.64
A18: e) Cobrador do Transporte Complementar (NR LC 238/2018) | B18: 148.66 | C18: 0.035 | D18: 5.2
A19: f) Ajudante de Transporte de Produtos Perigosos (NR LC 238/2018) | B19: 148.66 | C19: 0.035 | D19: 5.2
A20: 4 - Profissionais Autônomos de nível superior, não inscrito no município: (NR LC 057/2006)
A21: a) Engenheiros e Arquitetos, por projeto | B21: 728.27 | C21: 0.05 | D21: 36.41
A22: b) Demais Profissionais de nível superior, por serviço prestados | B22: 728.27 | C22: 0.05 | D22: 36.41
A23: 5 - Sociedade de Profissionais de Nível Superior:
A24: a) Por profissionais habilitado sócio, empregado ou não por profissionais | B24: Aplicar tabela nº 1
A25: 6 - Sociedade de Profissionais de nível médio:
A26: a) Por profissional habilitado, sócio, empregado ou não por profissional | B26: Aplicar tabela nº 2
A27: 7 - Sociedade de Profissionais de nível elementar:
A28: a) Por profissional habilitado, sócio, empregado ou não, por profissional | B28: Aplicar tabela nº 3
A29: 8 - Profissionais autônomos de nível médio, não inscrito no município, por serviços prestados | B29: 254.89 | C29: 0.05 | D29: 12.74
A30: 9 - Profissionais autônomos de nível elementar, não inscrito no Município, por serviços prestados | B30: 218.48 | C30: 0.05 | D30: 10.92
A31: 10 - Escritório de Serviços Contábeis: O valor devido mensalmente, ou não-sócio, empregado, ou não, que prestem serviços em nome do escritório (AC LC 092/2009) | B31: 25.48
A32: 11 - Cartórios (AC LC 240/2018) Preço do Serviço, deduzido dos repasses a terceiros por determinação legal | C32: 0.05
A33: 12 - EMPRESAS: (NR LCs 092/2009 e 240/2018) Base de Cálculo - Preço do Serviço x Alíquota
A34: a) Varrição, coleta, remoção, incineração, tratamento, reciclagem separação e destinação final de lixo, rejeitos e outros resíduos quaisquer (Item 7.09 da lista do art. 47) (NR LC 240/2018) | D34: 0.05
A35: b) Limpeza, manutenção e conservação de vias e logradouros públicos, imóveis, chaminés, piscinas, parques, jardins e congêneres (Item 7.10 da lista do art. 47) (NR LC 240/2018) | D35: 0.05
A36: c) Decoração e jardinagem, inclusive corte e poda de arvores. (Item 7.11 da lista do art. 47) | D36: 0.03
A37: d) Dedetização, desinfecção, desinsetização, imunização, higienização, desratização, pulverização e congêneres (Item 7.13 da lista do art. 47) | D37: 0.02
A38: e) Florestamento, reflorestamento, semeadura, adubação e congêneres. (item 7.16 da lista do art. 47) (NR LC 140/2011) | D38: 0.02
A39: f) Escoramento, contenção de encostas e serviços congêneres. (Item 7.15 da lista do art. 47). (Redação dada pelo art. 24 da Lei Complementar 140/2011) (NR LC 240/2018) | D39: 0.05
A40: g) Acompanhamento e fiscalização da execução de obras de engenharia, arquitetura e urbanismo. (item 7.19 da lista do art. 47) (NR LC 140/2011) | D40: 0.05
A41: h) Pesquisa, perfuração, cimentação, mergulho, perfilagem, concretação, testemunhagem, pescaria, estimulação e outros serviços relacionados com a exploração e explotação de petróleo, gás natural e de outros recursos minerais. (item 7.21 da lista do art. 47) (NR LC 140/2011) | D41: 0.05
A42: i) Nucleação e bombardeamento de nuvens e congêneres. (item 7.22 da lista do art. 47) (NR LC 140/2011) | D42: 0.02
A43: j) Ensino regular pré-escolar, fundamental, médio e superior, instrução, treinamento, orientação pedagógica e educacional, avaliação de conhecimento de qualquer natureza (Itens 8.01 e 8.02 da lista do art. 47) | D43: 0.03
A44: k) Lubrificação, limpeza, lustração, revisão, carga e recarga, conserto, restauração, blindagem, manutenção e conservação de máquinas, veículos, aparelhos, equipamentos, motores e elevadores ou de qualquer objeto, exceto peças e partes empregadas, que ficam sujeitas ao ICMS (Itens 14.01 da lista do art. 47) | D44: 0.02
A45: l) Instalação e montagem de aparelhos, máquinas equipamentos, inclusive montagem industrial, prestados aos usuários final, exclusivamente com material por ele fornecido. (Item 14.06 da lista do art. 47) | D45: 0.035
... A49: p) Disponibilização, sem cessão definitiva, de conteúdo (streaming) de áudio, vídeo, imagem e texto por meio da internet, respeitada a imunidade de livros, jornais e periódicos (Item 1.09 da Lista do art. 47) ➭ (AC LC 284/2022) | D49: 0.02
